wea/__init__.py
wea/wea.py
wea/backend/config.py
wea/backend/nominatim.py
wea/backend/openweather.py
wea/backend/weather.py
wea/frontend/art.py
wea/frontend/translations.py
wea/frontend/ui.py
wea_clt-0.0.9.dist-info/LICENSE
wea_clt-0.0.9.dist-info/METADATA
wea_clt-0.0.9.dist-info/WHEEL
wea_clt-0.0.9.dist-info/entry_points.txt
wea_clt-0.0.9.dist-info/top_level.txt
wea_clt-0.0.9.dist-info/RECORD
