Metadata-Version: 2.1
Name: wea-clt
Version: 0.0.9
Summary: A command-line tool to check the weather.
Home-page: https://github.com/f7olivera/wea
Author: f7olivera
Author-email: f7olivera@gmail.com
Classifier: Programming Language :: Python :: 3
Classifier: License :: OSI Approved :: MIT License
Classifier: Operating System :: OS Independent
License-File: LICENSE
Requires-Dist: colorama (~=0.4.4)
Requires-Dist: requests (~=2.26.0)
Requires-Dist: pytz (~=2021.3)
Requires-Dist: timezonefinder (~=5.2.0)
Requires-Dist: pick (~=1.2.0)
Requires-Dist: Babel (~=2.9.1)
